Metadata-Version: 2.2
Name: PySide6-stubs
Version: 6.7.3.0
Summary: PEP561 stub files for the *Qt for Python/PySide6* framework
Home-page: https://github.com/python-qt-tools/PySide6-stubs
Author: Philippe Fremy
Author-email: phil.fremy@free.fr
License: LGPL v2.1
Project-URL: Bug Tracker, https://github.com/python-qt-tool/pyside6-stubs/issues
Classifier: Development Status :: 5 - Production/Stable
Classifier: Programming Language :: Python :: 3
Classifier: License :: OSI Approved :: GNU Lesser General Public License v2 (LGPLv2)
Classifier: Operating System :: OS Independent
Classifier: Intended Audience :: Developers
Classifier: Typing :: Stubs Only
Requires-Python: >=3.7
License-File: LICENSE
Requires-Dist: mypy>=1.0
Requires-Dist: PySide6>=6.0
Provides-Extra: dev
Requires-Dist: pytest; extra == "dev"
